backup_runner-0.2.3.data/data/config/backup-runner-example.cfg
backuprunner/__init__.py
backuprunner/__main__.py
backuprunner/config.py
backuprunner/date_helper.py
backuprunner/mailer.py
backuprunner/backup/__init__.py
backuprunner/backup/backup.py
backuprunner/backup/mysql_backup.py
backuprunner/backup/path_backup.py
backuprunner/utils/__init__.py
backuprunner/utils/arg_parser.py
backuprunner/utils/config_file_args.py
backuprunner/utils/config_file_parser.py
backup_runner-0.2.3.dist-info/LICENSE
backup_runner-0.2.3.dist-info/METADATA
backup_runner-0.2.3.dist-info/WHEEL
backup_runner-0.2.3.dist-info/entry_points.txt
backup_runner-0.2.3.dist-info/top_level.txt
backup_runner-0.2.3.dist-info/RECORD
