Metadata-Version: 2.1
Name: backup-runner
Version: 0.2.3
Summary: Run a backup script on your local server
Home-page: https://github.com/Senth/backup-runner
Author: Matteus Magnusson
Author-email: senth.wallace@gmail.com
License: MIT
Platform: UNKNOWN
Classifier: Development Status :: 2 - Pre-Alpha
Classifier: License :: OSI Approved :: MIT License
Classifier: Environment :: Console
Classifier: Programming Language :: Python :: 3.8
Classifier: Programming Language :: Python :: 3.9
Classifier: Programming Language :: Python :: 3.10
Requires-Python: >=3.8
License-File: LICENSE
Requires-Dist: psutil
Requires-Dist: tealprint
Requires-Dist: blulib
